kyna/__init__.py
kyna/main.py
kyna-0.4.7.dist-info/METADATA
kyna-0.4.7.dist-info/WHEEL
kyna-0.4.7.dist-info/top_level.txt
kyna-0.4.7.dist-info/RECORD
